libcalculus.cpython-38-x86_64-linux-gnu.so
libcalculus-1.0.2.dist-info/LICENSE.txt
libcalculus-1.0.2.dist-info/METADATA
libcalculus-1.0.2.dist-info/WHEEL
libcalculus-1.0.2.dist-info/top_level.txt
libcalculus-1.0.2.dist-info/RECORD
