Metadata-Version: 2.1
Name: libcalculus
Version: 1.0.2
Summary: Real/Complex analysis library for Python 3.
Home-page: https://pypi.org/project/libcalculus
Author: Ariel Terkeltoub
Author-email: ariter777@gmail.com
License: UNKNOWN
Project-URL: Documentation, https://libcalculus.readthedocs.io/en/latest/
Project-URL: Source Code, https://gitlab.com/ariter777/libcalculus
Keywords: analysis,real,complex,integral,derivative
Platform: UNKNOWN
Classifier: Development Status :: 4 - Beta
Classifier: Intended Audience :: Developers
Classifier: License :: OSI Approved :: BSD License
Classifier: Programming Language :: Python :: 3
Classifier: Programming Language :: Python :: 3.7
Classifier: Programming Language :: Python :: 3.8
Requires-Dist: Cython (>=0.29.28)
Requires-Dist: numpy (>=1.21)
